
{
  "dccons": [
{ "path" : "https://bongzreal.github.io/레바콘/레바그안키.png" },
{ "path" : "https://bongzreal.github.io/레바콘/레바꺄륵.png" },
{ "path" : "https://bongzreal.github.io/레바콘/레바띠용.png" },
{ "path" : "https://bongzreal.github.io/레바콘/레바모르겠다.png" },
{ "path" : "https://bongzreal.github.io/레바콘/레바불안.png" },
{ "path" : "https://bongzreal.github.io/레바콘/레바설명.png" },
{ "path" : "https://bongzreal.github.io/레바콘/레바어쩌라고.png" },
{ "path" : "https://bongzreal.github.io/레바콘/레바언행불일치.png" },
{ "path" : "https://bongzreal.github.io/레바콘/레바와아.png" },
{ "path" : "https://bongzreal.github.io/레바콘/레바이제볼만.png" },
{ "path" : "https://bongzreal.github.io/레바콘/레바제일미친.png" },
{ "path" : "https://bongzreal.github.io/레바콘/레바쾅쾅쾅.png" },
{ "path" : "https://bongzreal.github.io/레바콘/레바쾌락.png" },
{ "path" : "https://bongzreal.github.io/레바콘/레바탕탕.png" },
{ "path" : "https://bongzreal.github.io/레바콘/레바팝콘.png" },
{ "path" : "https://bongzreal.github.io/레바콘/레바팝콘2.png" },
{ "path" : "https://bongzreal.github.io/레바콘/레바한참부족.png" },
{ "path" : "https://bongzreal.github.io/레바콘/레바핥짝.png" }

  ]
}
